rest3client/__init__.py
rest3client/rest.py
rest3client/restcli.py
rest3client/restclient.py
rest3client/ssladapter.py
rest3client-0.7.4.dist-info/METADATA
rest3client-0.7.4.dist-info/WHEEL
rest3client-0.7.4.dist-info/entry_points.txt
rest3client-0.7.4.dist-info/namespace_packages.txt
rest3client-0.7.4.dist-info/top_level.txt
rest3client-0.7.4.dist-info/zip-safe
rest3client-0.7.4.dist-info/RECORD
